unike/__init__.py
unike/version.py
unike/config/HPOTrainer.py
unike/config/Tester.py
unike/config/Trainer.py
unike/config/__init__.py
unike/data/BernSampler.py
unike/data/CompGCNSampler.py
unike/data/CompGCNTestSampler.py
unike/data/KGEDataLoader.py
unike/data/KGReader.py
unike/data/RGCNSampler.py
unike/data/RGCNTestSampler.py
unike/data/RevSampler.py
unike/data/TestSampler.py
unike/data/TradSampler.py
unike/data/TradTestSampler.py
unike/data/UniSampler.py
unike/data/__init__.py
unike/module/BaseModule.py
unike/module/__init__.py
unike/module/loss/CompGCNLoss.py
unike/module/loss/Loss.py
unike/module/loss/MarginLoss.py
unike/module/loss/RGCNLoss.py
unike/module/loss/SigmoidLoss.py
unike/module/loss/SoftplusLoss.py
unike/module/loss/__init__.py
unike/module/model/Analogy.py
unike/module/model/CompGCN.py
unike/module/model/ComplEx.py
unike/module/model/DistMult.py
unike/module/model/HolE.py
unike/module/model/Model.py
unike/module/model/RESCAL.py
unike/module/model/RGCN.py
unike/module/model/RotatE.py
unike/module/model/SimplE.py
unike/module/model/TransD.py
unike/module/model/TransE.py
unike/module/model/TransH.py
unike/module/model/TransR.py
unike/module/model/__init__.py
unike/module/strategy/CompGCNSampling.py
unike/module/strategy/NegativeSampling.py
unike/module/strategy/RGCNSampling.py
unike/module/strategy/Strategy.py
unike/module/strategy/__init__.py
unike/utils/EarlyStopping.py
unike/utils/Link.py
unike/utils/Timer.py
unike/utils/WandbLogger.py
unike/utils/__init__.py
unike/utils/tools.py
unike-3.3.1.dist-info/METADATA
unike-3.3.1.dist-info/WHEEL
unike-3.3.1.dist-info/entry_points.txt
unike-3.3.1.dist-info/licenses/LICENSE
unike-3.3.1.dist-info/RECORD
