Metadata-Version: 2.4
Name: unike
Version: 3.3.1
Summary: 基于 OpenKE-PyTorch 开发的知识图谱嵌入工具包
Author-email: LuYF-Lemon-love <3555028709@qq.com>, wangtao <wangtao.cpu@gmail.com>
License-File: LICENSE
Requires-Python: >=3.10
Requires-Dist: accelerate>=0.20.3
Requires-Dist: dgl
Requires-Dist: loguru
Requires-Dist: numpy==1.24.0
Requires-Dist: pandas>=1.1.5
Requires-Dist: swanlab
Requires-Dist: torchdata==0.7.0
Requires-Dist: tqdm
Requires-Dist: wandb
